{
  "type": "FeatureCollection", 
  "features": [
    {
      "geometry": {
        "type": "Point", 
        "coordinates": [
          -122.57335881414666, 
          37.893197205374946
        ]
      }, 
      "type": "Feature", 
      "properties": {
        "Len_Up": 6.2, 
        "Av_S_Up": 13.5, 
        "Length_3D": 18.8, 
        "Len_Down": 12.6, 
        "Max_S_Down": 1.3, 
        "Min_Z": 42.4, 
        "H_Down": 0.3, 
        "ET_ID": 46, 
        "trail_name": "Bridge 1", 
        "ET_Y": 4194050.9169, 
        "ET_ORDER": 0.0, 
        "Max_S_Up": 13.5, 
        "ET_IDP": 46, 
        "ET_IDR": "46_0", 
        "H_Up": 1.4, 
        "ET_X": 537512.3019, 
        "Av_S_Down": 1.3, 
        "ET_Z": 42.71533, 
        "Length_2D": 18.6, 
        "Max_Z": 43.9
      }
    }, 
    {
      "geometry": {
        "type": "Point", 
        "coordinates": [
          -122.57322219567516, 
          37.89323147328672
        ]
      }, 
      "type": "Feature", 
      "properties": {
        "Len_Up": 6.2, 
        "Av_S_Up": 13.5, 
        "Length_3D": 18.8, 
        "Len_Down": 12.6, 
        "Max_S_Down": 1.3, 
        "Min_Z": 42.4, 
        "H_Down": 0.3, 
        "ET_ID": 46, 
        "trail_name": "Bridge 1", 
        "ET_Y": 4194054.7739, 
        "ET_ORDER": 0.6758, 
        "Max_S_Up": 13.5, 
        "ET_IDP": 46, 
        "ET_IDR": "46_0", 
        "H_Up": 1.4, 
        "ET_X": 537524.2967, 
        "Av_S_Down": 1.3, 
        "ET_Z": 42.43268, 
        "Length_2D": 18.6, 
        "Max_Z": 43.9
      }
    }, 
    {
      "geometry": {
        "type": "Point", 
        "coordinates": [
          -122.57316864950984, 
          37.89326565022363
        ]
      }, 
      "type": "Feature", 
      "properties": {
        "Len_Up": 6.2, 
        "Av_S_Up": 13.5, 
        "Length_3D": 18.8, 
        "Len_Down": 12.6, 
        "Max_S_Down": 1.3, 
        "Min_Z": 42.4, 
        "H_Down": 0.3, 
        "ET_ID": 46, 
        "trail_name": "Bridge 1", 
        "ET_Y": 4194058.5874, 
        "ET_ORDER": 1.0, 
        "Max_S_Up": 13.5, 
        "ET_IDP": 46, 
        "ET_IDR": "46_0", 
        "H_Up": 1.4, 
        "ET_X": 537528.9874, 
        "Av_S_Down": 1.3, 
        "ET_Z": 43.88225, 
        "Length_2D": 18.6, 
        "Max_Z": 43.9
      }
    }
  ]
}